{
    "type": "dummy_data",
    "version": "1.0",
    "Header": "Transfer function measurement",
    "Data": {
        "channel names": [
            "frequency in Hz",
            "transfer_function",
            "tuned_amplitude in uV"
        ],
        "values": [
            [
                1000,
                1.5e-11,
                200000
            ],
            [
                10000,
                1.5e-11,
                200000
            ],
            [
                100000,
                1.5e-11,
                200000
            ]
        ]
    }
}